json_simple_validator/__init__.py
json_simple_validator/validation.py
json_simple_validator-1.0.1.dist-info/LICENCE
json_simple_validator-1.0.1.dist-info/METADATA
json_simple_validator-1.0.1.dist-info/WHEEL
json_simple_validator-1.0.1.dist-info/top_level.txt
json_simple_validator-1.0.1.dist-info/RECORD
